airtable_to_sqlite/__about__.py
airtable_to_sqlite/__init__.py
airtable_to_sqlite/__main__.py
airtable_to_sqlite/constants.py
airtable_to_sqlite/main.py
airtable_to_sqlite/schema.py
airtable_to_sqlite/cli/__init__.py
airtable_to_sqlite-0.2.1.dist-info/METADATA
airtable_to_sqlite-0.2.1.dist-info/WHEEL
airtable_to_sqlite-0.2.1.dist-info/entry_points.txt
airtable_to_sqlite-0.2.1.dist-info/licenses/LICENSE.txt
airtable_to_sqlite-0.2.1.dist-info/RECORD
