Metadata-Version: 2.1
Name: airtable-to-sqlite
Version: 0.2.1
Summary: Export Airtable bases to an sqlite database
Project-URL: Documentation, https://github.com/kanedata/airtable-to-sqlite#readme
Project-URL: Issues, https://github.com/kanedata/airtable-to-sqlite/issues
Project-URL: Source, https://github.com/kanedata/airtable-to-sqlite
Author-email: David Kane <david@dkane.net>
License-Expression: MIT
License-File: LICENSE.txt
Classifier: Development Status :: 4 - Beta
Classifier: Programming Language :: Python
Classifier: Programming Language :: Python :: 3.8
Classifier: Programming Language :: Python :: 3.9
Classifier: Programming Language :: Python :: 3.10
Classifier: Programming Language :: Python :: 3.11
Classifier: Programming Language :: Python :: 3.12
Classifier: Programming Language :: Python :: Implementation :: CPython
Classifier: Programming Language :: Python :: Implementation :: PyPy
Requires-Python: >=3.7
Requires-Dist: click
Requires-Dist: diskcache
Requires-Dist: pyairtable==2.2.*
Requires-Dist: python-dotenv
Requires-Dist: sqlite-utils
Requires-Dist: tqdm
